anujstrike/__init__.py
anujstrike/gui.py
anujstrike/main.py
anujstrike/core/__init__.py
anujstrike/core/brute_force.py
anujstrike/core/network_attacks.py
anujstrike/core/utils.py
anujstrike/core/web_exploits.py
anujstrike-0.1.6.dist-info/METADATA
anujstrike-0.1.6.dist-info/WHEEL
anujstrike-0.1.6.dist-info/entry_points.txt
anujstrike-0.1.6.dist-info/top_level.txt
anujstrike-0.1.6.dist-info/RECORD
