Metadata-Version: 2.4
Name: anujstrike
Version: 0.1.6
Summary: AnujStrike Offensive Toolkit with GUI
Home-page: https://pypi.org/project/anujstrike/
Author: Anuj Prajapati
Author-email: Anuj Prajapati <anujprajapatiwork.2109@gmail.com>
Requires-Python: >=3.6
Requires-Dist: requests
Requires-Dist: scapy
Requires-Dist: psutil
Dynamic: author
Dynamic: home-page
Dynamic: requires-python
